setup.cfg
setup.py
scripts/smarterling
smarterling/__init__.py
smarterling.egg-info/PKG-INFO
smarterling.egg-info/SOURCES.txt
smarterling.egg-info/dependency_links.txt
smarterling.egg-info/requires.txt
smarterling.egg-info/top_level.txt