Metadata-Version: 1.1
Name: smarterling
Version: 0.4
Summary: Python based command line tool for performing automated tasks with Smartling (http://www.smartling.com).
Home-page: https://github.com/Cheers-Dev/smarterling
Author: Brian C. Dilley - Flipagram
Author-email: brian@flipagram.com
License: UNKNOWN
Download-URL: https://github.com/Cheers-Dev/smarterling
Platform: any
Classifier: Intended Audience :: Developers
